g3w_config_scripts/__init__.py
g3w_config_scripts/g3w_branding.py
g3w_config_scripts/g3w_config.py
g3w_config_scripts/g3w_config_gen.py
g3w_config_scripts/g3w_dev_setup.py
g3w_config_scripts/g3w_prod_setup.py
g3wsuite_config_scripts-0.6.2.dist-info/METADATA
g3wsuite_config_scripts-0.6.2.dist-info/WHEEL
g3wsuite_config_scripts-0.6.2.dist-info/entry_points.txt
g3wsuite_config_scripts-0.6.2.dist-info/top_level.txt
g3wsuite_config_scripts-0.6.2.dist-info/RECORD
