Metadata-Version: 2.4
Name: g3wsuite_config_scripts
Version: 0.6.2
Summary: Configuration scripts for the g3w suite setup
Home-page: https://github.com/moovida/g3wsuite_config_scripts
Author: Andrea Antonello
Author-email: andrea.antonello@gmail.com
Classifier: Programming Language :: Python :: 3
Classifier: License :: OSI Approved :: MIT License
Classifier: Operating System :: OS Independent
Requires-Python: >=3.7
Requires-Dist: pillow>=11.1.0
Dynamic: author
Dynamic: author-email
Dynamic: classifier
Dynamic: description
Dynamic: description-content-type
Dynamic: home-page
Dynamic: requires-dist
Dynamic: requires-python
Dynamic: summary
